impdar-1.2.1.dist-info/RECORD
impdar-1.2.1.dist-info/WHEEL
impdar-1.2.1.dist-info/entry_points.txt
impdar-1.2.1.dist-info/top_level.txt
impdar-1.2.1.dist-info/METADATA
impdar-1.2.1.dist-info/licenses/LICENSE
impdar/__init__.py
impdar/bin/impproc.py
impdar/bin/impplot.py
impdar/bin/apdar.py
impdar/bin/__init__.py
impdar/bin/impdarexec.py
impdar/bin/imppick.py
impdar/gui/__init__.py
impdar/gui/pickgui.py
impdar/gui/ui/mplfigcanvaswidget.py
impdar/gui/ui/__init__.py
impdar/gui/ui/RawPickGUI.py
impdar/lib/permittivity_models.py
impdar/lib/picklib.py
impdar/lib/Picks.py
impdar/lib/plot.py
impdar/lib/convert.py
impdar/lib/__init__.py
impdar/lib/gpslib.py
impdar/lib/PickParameters.py
impdar/lib/Crop.py
impdar/lib/RadarFlags.py
impdar/lib/LastTrace.py
impdar/lib/process.py
impdar/lib/LeaderTrailer.py
impdar/lib/ImpdarError.py
impdar/lib/NoInitRadarData.py
impdar/lib/migrationlib/mig_su.py
impdar/lib/migrationlib/__init__.py
impdar/lib/migrationlib/mig_cython.cpython-311-darwin.so
impdar/lib/migrationlib/_mig_cython.pyx
impdar/lib/migrationlib/mig_python.py
impdar/lib/analysis/attenuation.py
impdar/lib/analysis/geometric_power_corrections.py
impdar/lib/analysis/Roughness.py
impdar/lib/analysis/__init__.py
impdar/lib/analysis/continuity_index.py
impdar/lib/load/load_delores.py
impdar/lib/load/load_mcords.py
impdar/lib/load/load_seidart.py
impdar/lib/load/load_stomat.py
impdar/lib/load/load_gssi.py
impdar/lib/load/load_UoA.py
impdar/lib/load/__init__.py
impdar/lib/load/load_segy.py
impdar/lib/load/load_olaf.py
impdar/lib/load/loading_utils.py
impdar/lib/load/load_gprMax.py
impdar/lib/load/load_ramac.py
impdar/lib/load/load_apres_profile.py
impdar/lib/load/load_pulse_ekko.py
impdar/lib/load/load_bsi.py
impdar/lib/load/load_osu.py
impdar/lib/load/load_tek.py
impdar/lib/ApresData/_ApresDataProcessing.py
impdar/lib/ApresData/load_quadpol.py
impdar/lib/ApresData/load_apres.py
impdar/lib/ApresData/_ApresDataSaving.py
impdar/lib/ApresData/_QuadPolProcessing.py
impdar/lib/ApresData/_coherence.pyx
impdar/lib/ApresData/__init__.py
impdar/lib/ApresData/_TimeDiffProcessing.py
impdar/lib/ApresData/ApresHeader.py
