Metadata-Version: 2.4
Name: impdar
Version: 1.2.1
Summary: Scripts for impulse radar
Author-email: David Lilien <dlilien@iu.edu>
License: LICENSE
Requires-Python: >=3.8
License-File: LICENSE
Requires-Dist: numpy>1.12.0
Requires-Dist: scipy>0.19.0
Requires-Dist: matplotlib>2.0.0
Requires-Dist: h5py
Requires-Dist: segyio
Dynamic: license-file
